quicksample101/__init__.py
quicksample101/quicksample101.py
quicksample101-0.1.dist-info/METADATA
quicksample101-0.1.dist-info/WHEEL
quicksample101-0.1.dist-info/top_level.txt
quicksample101-0.1.dist-info/RECORD
