Metadata-Version: 2.1
Name: quicksample101
Version: 0.1
Summary: Quicksample Test Package
Author: Amit Joshi
Classifier: Programming Language :: Python :: 3
Classifier: License :: OSI Approved :: MIT License
Classifier: Operating System :: OS Independent
Requires-Python: >=3.6
